astrocal/__init__.py
astrocal/astrometry.py
astrocal/cpi.py
astrocal/master.py
astrocal/photometry.py
astrocal/reduction.py
astrocal-0.1.0.dist-info/licenses/LICENSE
astrocal-0.1.0.dist-info/METADATA
astrocal-0.1.0.dist-info/WHEEL
astrocal-0.1.0.dist-info/top_level.txt
astrocal-0.1.0.dist-info/RECORD
