Metadata-Version: 2.4
Name: astrocal
Version: 0.1.0
Summary: Package to calibrate astro images and analyse them
Author-email: Aurélien Genin <aurelien.genin@polytechnique.org>
Project-URL: Source, https://github.com/AstroAure/AstroCal
Classifier: Programming Language :: Python :: 3
Classifier: License :: OSI Approved :: GNU General Public License v3 or later (GPLv3+)
Classifier: Operating System :: OS Independent
Requires-Python: >=3.9
License-File: LICENSE
Requires-Dist: numpy
Requires-Dist: astropy
Requires-Dist: astroquery
Requires-Dist: photutils
Requires-Dist: reproject
Requires-Dist: scikit-learn
Requires-Dist: scipy>=1.12.0
Requires-Dist: Pillow>=10.4.0
Dynamic: license-file
